mechanicalsoup/__init__.py
mechanicalsoup/__version__.py
mechanicalsoup/browser.py
mechanicalsoup/form.py
mechanicalsoup/stateful_browser.py
mechanicalsoup/utils.py
MechanicalSoup-1.3.0.dist-info/LICENSE
MechanicalSoup-1.3.0.dist-info/METADATA
MechanicalSoup-1.3.0.dist-info/WHEEL
MechanicalSoup-1.3.0.dist-info/top_level.txt
MechanicalSoup-1.3.0.dist-info/RECORD
