Metadata-Version: 2.1
Name: MechanicalSoup
Version: 1.3.0
Summary: A Python library for automating interaction with websites
Home-page: https://mechanicalsoup.readthedocs.io/
License: MIT
Project-URL: Source, https://github.com/MechanicalSoup/MechanicalSoup
Classifier: License :: OSI Approved :: MIT License
Classifier: Programming Language :: Python :: 3
Classifier: Programming Language :: Python :: 3.6
Classifier: Programming Language :: Python :: 3.7
Classifier: Programming Language :: Python :: 3.8
Classifier: Programming Language :: Python :: 3.9
Classifier: Programming Language :: Python :: 3.10
Classifier: Programming Language :: Python :: 3.11
Classifier: Programming Language :: Python :: 3 :: Only
Requires-Python: >=3.6
License-File: LICENSE
